plane_adk/__init__.py
plane_adk/agent/__init__.py
plane_adk/agent/agent.py
plane_adk/agent/models.py
plane_adk/agent/handlers/__init__.py
plane_adk/agent/handlers/handlers.py
plane_adk-0.1.1.dist-info/licenses/LICENSE
plane_adk-0.1.1.dist-info/METADATA
plane_adk-0.1.1.dist-info/WHEEL
plane_adk-0.1.1.dist-info/top_level.txt
plane_adk-0.1.1.dist-info/RECORD
