Metadata-Version: 2.4
Name: plane-adk
Version: 0.1.1
Summary: Plane Agent Development Kit
Author-email: Plane Engineering <engineering@plane.so>
License-Expression: MIT
Requires-Python: >=3.9
License-File: LICENSE
Requires-Dist: pydantic>=2
Requires-Dist: requests>=2.32.3
Requires-Dist: plane-sdk==0.1.9
Dynamic: license-file
